inmanta_tests/__init__.py
inmanta_tests/conftest.py
inmanta_tests/plugin.py
inmanta_tests/utils.py
inmanta_tests/data/server.crt
inmanta_tests/data/server.open.key
inmanta_tests/data/ca/enduser-certs/server.chain
inmanta_tests/data/ca/enduser-certs/server.crt
inmanta_tests/data/ca/enduser-certs/server.key
inmanta_tests/data/ca/enduser-certs/server.key.open
inmanta_tests/db/common.py
inmanta_tests/db/simple_project/main.cf
inmanta_tests/db/simple_project/project.yml
inmanta_tests/db/simple_project/requirements.txt
pytest_inmanta_extensions-18.0.0.dist-info/METADATA
pytest_inmanta_extensions-18.0.0.dist-info/WHEEL
pytest_inmanta_extensions-18.0.0.dist-info/entry_points.txt
pytest_inmanta_extensions-18.0.0.dist-info/top_level.txt
pytest_inmanta_extensions-18.0.0.dist-info/RECORD
