Metadata-Version: 2.4
Name: pytest-inmanta-extensions
Version: 18.0.0
Summary: Inmanta tests package
Home-page: https://github.com/inmanta/inmanta
Author: Inmanta
Author-email: code@inmanta.com
License: Apache Software License 2
Project-URL: Bug Tracker, https://github.com/inmanta/inmanta-core/issues
Keywords: pytest inmanta tests
Classifier: Development Status :: 5 - Production/Stable
Classifier: Intended Audience :: Developers
Classifier: Operating System :: OS Independent
Classifier: Topic :: Software Development
Classifier: Topic :: Software Development :: Testing
Classifier: Programming Language :: Python :: 3.5
Classifier: Programming Language :: Python :: 3.6
Classifier: Programming Language :: Python :: 3.7
Classifier: Framework :: Pytest
Requires-Python: >=3.6
Requires-Dist: asyncpg
Requires-Dist: click
Requires-Dist: inmanta-core~=18.0.0.0.dev
Requires-Dist: pip2pi
Requires-Dist: pyformance
Requires-Dist: pytest-asyncio
Requires-Dist: pytest-env
Requires-Dist: pytest-postgresql>=4
Requires-Dist: psycopg>=3
Requires-Dist: tornado
Dynamic: author
Dynamic: author-email
Dynamic: classifier
Dynamic: description
Dynamic: description-content-type
Dynamic: home-page
Dynamic: keywords
Dynamic: license
Dynamic: project-url
Dynamic: requires-dist
Dynamic: requires-python
Dynamic: summary
